[
    {
        "branch":"8.0",
        "depth":1,
        "is_dirty":false,
        "name":"odoo",
        "path":"odoo",
        "repo_url":{
            "origin":"https://github.com/vauxoo/odoo.git"
        },
        "type":"git"
    },
    {
        "branch":"8.0",
        "depth":1,
        "name":"odoo-mexico-v2",
        "path":"extra_addons/oml",
        "repo_url":{
            "origin":"git@github.com:vauxoo/odoo-mexico-v2.git"
        },
        "type":"git"
    },
    {
        "branch":"8.0",
        "depth":1,
        "name":"cms",
        "path":"extra_addons/cms",
        "repo_url":{
            "origin":"git@github.com:vauxoo/cms.git"
        },
        "type":"git"
    },
    {
        "branch":"8.0",
        "depth":1,
        "name":"odoo-network",
        "path":"extra_addons/odoo_network",
        "repo_url":{
            "origin":"git@github.com:Vauxoo/odoo-network.git"
        },
        "type":"git"
    },
    {
        "branch":"master",
        "depth":1,
        "name":"server-tools",
        "path":"extra_addons/server_tools",
        "repo_url":{
            "origin":"git@github.com:vauxoo/server-tools.git"
        },
        "type":"git"
    },
    {
        "branch":"8.0",
        "depth":1,
        "name":"instance-vauxoo-com",
        "path":"extra_addons/vauxoo",
        "repo_url":{
            "origin":"git@github.com:vauxoo/instance-vauxoo-com.git"
        },
        "type":"git"
    },
    {
        "branch":"8.0",
        "depth":1,
        "name":"odoo-ifrs",
        "path":"extra_addons/odoo_ifrs",
        "repo_url":{
            "origin":"git@github.com:Vauxoo/odoo-ifrs.git"
        },
        "type":"git"
    },
    {
        "branch":"8.0",
        "depth":1,
        "name":"odoo-afr",
        "path":"extra_addons/odoo_afr",
        "repo_url":{
            "origin":"git@github.com:Vauxoo/odoo-afr.git"
        },
        "type":"git"
    },
    {
        "branch":"7.0",
        "depth":1,
        "name":"l10n-mx-invoice-pdf-formats",
        "path":"extra_addons/pdf_format",
        "repo_url":{
            "origin":"git@github.com:Vauxoo/l10n-mx-invoice-pdf-formats.git"
        },
        "type":"git"
    },
    {
        "branch":"8.0",
        "depth":1,
        "name":"odoo-themes",
        "path":"extra_addons/odoo_themes",
        "repo_url":{
            "origin":"git@github.com:Vauxoo/odoo-themes.git"
        },
        "type":"git"
    },
    {
        "branch":"8.0",
        "depth":1,
        "name":"addons-vauxoo",
        "path":"extra_addons/addons_vauxoo",
        "repo_url":{
            "origin":"git@github.com:Vauxoo/addons-vauxoo.git"
        },
        "type":"git"
    }
]
